msgspec_settings/__init__.py
msgspec_settings/exceptions.py
msgspec_settings/loading.py
msgspec_settings/models.py
msgspec_settings/parsing.py
msgspec_settings/py.typed
msgspec_settings/settings.py
msgspec_settings/types.py
msgspec_settings-0.1.0.dist-info/METADATA
msgspec_settings-0.1.0.dist-info/WHEEL
msgspec_settings-0.1.0.dist-info/licenses/LICENSE
msgspec_settings-0.1.0.dist-info/RECORD
