Metadata-Version: 2.4
Name: msgspec-settings
Version: 0.1.0
Summary: Type-safe settings from environment variables and Docker secrets using msgspec
Project-URL: Repository, https://github.com/qqqoid/msgspec-settings
Project-URL: Issues, https://github.com/qqqoid/msgspec-settings/issues
Author-email: "Salavat D. Samigoullin" <qqq@oid.su>
License: MIT
License-File: LICENSE
Keywords: config,configuration,docker-secrets,environment-variables,msgspec,settings,type-safe,validation
Classifier: Development Status :: 3 - Alpha
Classifier: Intended Audience :: Developers
Classifier: License :: OSI Approved :: MIT License
Classifier: Programming Language :: Python :: 3
Classifier: Programming Language :: Python :: 3.13
Classifier: Topic :: Software Development :: Libraries :: Python Modules
Classifier: Topic :: System :: Systems Administration
Classifier: Typing :: Typed
Requires-Python: >=3.13
Requires-Dist: msgspec>=0.20.0
